{
    "wifi": {
        "ssid": "ssid",
        "password": "password"
    },
    "mqtt": {
        "broker": "example.com",
        "port": 8883,
        "topic": "lilygo/topic/1",
        "user": "user1",
        "password": "password1",
        "certificate_enable": false,
        "certificate": "1234567890abcdefghijklmnopqrstuvwxyz"
    },
    "device": {
        "name": "atom1",
        "jiggler": true,
        "setup_mode": true,
        "keyboard_enable": true,
        "admin": "admin",
        "password": "password"
    }
}
